{"name":"Frontend-bootstrap","body":"# Bootstrap repository for frontend development\r\n\r\nThis is a bootstrap repository for kickstart developing the frontend of web applications with [backbone.js](http://documentcloud.github.com/backbone/), [json2.js](https://github.com/douglascrockford/JSON-js), [underscore](https://github.com/documentcloud/underscore) and [twitter bootstrap](https://github.com/twitter/bootstrap) including the [glyphicons](http://glyphicons.com/). This repository if free for use and changes. You can do whatever you want, though please check the license models of the included libraries mentioned before.\r\n\r\n## How to kickstart\r\n\r\n    $ git clone git@github.com:rendro/frontend-bootstrap.git frontend\r\n    $ cd frontend\r\n    $ make\r\n\r\n## Dependencies\r\n\r\nTo use this tool, you need the the following few things installed:\r\n\r\n* [less](http://lesscss.org/)\r\n* [coffeescript](http://coffeescript.org/)\r\n* [watchr](https://github.com/mynyml/watchr)\r\n* creativity and mindblown awesomeness\r\n\r\n## Make commands\r\n\r\n* `$ make` or `$ make all`: compiles the less file _assets/css/less/style.less_ to _assets/css/style.css_ and the coffescript file _assets/js/app.coffee_ to _assets/js/app.js_\r\n* `$ make less`: only compiles the less file\r\n* `$ make watch-less`: watch less files and trigger the `make less` command on changes\r\n* `$ make coffee`: Brew some coffee and relax. Ok this command really compiles the coffescript file app.coffee\r\n* `$ make watch-coffee`: watch the coffeescript file and tigger the `make coffee` command on changes\r\n\r\n","tagline":"Bootstrap repository for kickstart frontend development with backbone and twitter bootstrap less files","google":"","note":"Don't delete this file! It's used internally to help with page regeneration."}